ethereum/__init__.py
ethereum/_solidity.py
ethereum/abi.py
ethereum/blocks.py
ethereum/bloom.py
ethereum/chain.py
ethereum/compress.py
ethereum/config.py
ethereum/db.py
ethereum/ethash.py
ethereum/ethash_utils.py
ethereum/ethpow.py
ethereum/exceptions.py
ethereum/fast_rlp.py
ethereum/fastvm.py
ethereum/keys.py
ethereum/numpysha3.py
ethereum/opcodes.py
ethereum/processblock.py
ethereum/pruning_trie.py
ethereum/refcount_db.py
ethereum/securetrie.py
ethereum/slogging.py
ethereum/specials.py
ethereum/spv.py
ethereum/tester.py
ethereum/testutils.py
ethereum/transactions.py
ethereum/trie.py
ethereum/utils.py
ethereum/vm.py
ethereum/tests/__init__.py
ethereum/tests/_broken_state.logging..py
ethereum/tests/benchmark_db.py
ethereum/tests/bintrie.py
ethereum/tests/conftest.py
ethereum/tests/profile_vm.py
ethereum/tests/rest_pow.py
ethereum/tests/stress_test.py
ethereum/tests/test_abi.py
ethereum/tests/test_blockhashes.py
ethereum/tests/test_blocks.py
ethereum/tests/test_bloom.py
ethereum/tests/test_chain.py
ethereum/tests/test_compress.py
ethereum/tests/test_contracts.py
ethereum/tests/test_db.py
ethereum/tests/test_ethash.py
ethereum/tests/test_genesis.py
ethereum/tests/test_keys.py
ethereum/tests/test_logging.py
ethereum/tests/test_pruning_trie.py
ethereum/tests/test_remoteblocks.py
ethereum/tests/test_serialization.py
ethereum/tests/test_solidity.py
ethereum/tests/test_state.py
ethereum/tests/test_transactions.py
ethereum/tests/test_trie.py
ethereum/tests/test_trie_next_prev.py
ethereum/tests/test_vm.py
ethereum/tests/test_vm_failing.py
ethereum/tests/utils.py
ethereum-1.1.0.dist-info/DESCRIPTION.rst
ethereum-1.1.0.dist-info/entry_points.txt
ethereum-1.1.0.dist-info/METADATA
ethereum-1.1.0.dist-info/metadata.json
ethereum-1.1.0.dist-info/RECORD
ethereum-1.1.0.dist-info/top_level.txt
ethereum-1.1.0.dist-info/WHEEL
tools/__init__.py
tools/fixture_to_example.py
tools/keystorer.py
tools/perftest.py
tools/random_vm_test_generator.py
tools/vm_test_generator.py
