Metadata-Version: 2.0
Name: ethereum
Version: 1.1.0
Summary: Next generation cryptocurrency network
Home-page: https://github.com/ethereum/pyethereum/
Author: UNKNOWN
Author-email: UNKNOWN
License: UNKNOWN
Platform: UNKNOWN
Requires-Dist: repoze.lru
Requires-Dist: PyYAML
Requires-Dist: pysha3
Requires-Dist: pbkdf2
Requires-Dist: bitcoin
Requires-Dist: pycryptodome (>=3.3.1)
Requires-Dist: scrypt
Requires-Dist: rlp (==0.4.4)
Requires-Dist: pyethash
